Workbook

Sheet Chart or Accounts
A1: Account No | B1: Account Name | C1: Account Type | D1: Normal Balance
A2: 101 | B2: Cash | C2: Assets | D2: Debit
A3: 102 | B3: Accounts Receivable | C3: Assets | D3: Debit
A4: 103 | B4: Prepaid Insurance | C4: Assets | D4: Debit
A5: 104 | B5: Office Equipments | C5: Assets | D5: Debit
A6: 201 | B6: Accounts Payable | C6: Liability | D6: Credit
A7: 202 | B7: Salaries Payable | C7: Liability | D7: Credit
A8: 203 | B8: Unearned Revenue | C8: Liability | D8: Credit
A9: 301 | B9: Owner's Capital | C9: Equity | D9: Credit
A10: 401 | B10: Service Revenue | C10: Revenue | D10: Credit
A11: 501 | B11: Rent Expense | C11: Expense | D11: Debit
A12: 502 | B12: Office Supplies Expenses | C12: Expense | D12: Debit
A13: 503 | B13: Salaries Expense | C13: Expense | D13: Debit
A14: 504 | B14: Insurance Expense | C14: Expense | D14: Debit

Sheet Journal
A1: Date | B1: Entry ID | C1: Account Name | D1: Description | E1: Debit | F1: Credit
A2: 46235 | B2: 1 | C2: Cash | D2: Initial owner investment | E2: 10000 | F2: 0
A3: 46235 | B3: 1 | C3: Owner's Capital | D3: Initial owner investment | E3: 0 | F3: 10000
A4: 46236 | B4: 2 | C4: ='Chart or Accounts'!B11 -> Rent Expense | D4: Paid office rent for August | E4: 1200 | F4: 0
A5: 46236 | B5: 2 | C5: Cash | D5: Paid office rent for August | E5: 0 | F5: 1200
A6: 46238 | B6: 3 | C6: ='Chart or Accounts'!B5 -> Office Equipments | D6: Purchased IT hardware on credit | E6: 3500 | F6: 0
A7: 46238 | B7: 3 | C7: ='Chart or Accounts'!B6 -> Accounts Payable | D7: Purchased IT hardware on credit | E7: 0 | F7: 3500
A8: 46240 | B8: 4 | C8: ='Chart or Accounts'!B12 -> Office Supplies Expenses | D8: Purchased Office Supplies | E8: 300 | F8: 0
A9: 46240 | B9: 4 | C9: Cash | D9: Purchased Office Supplies | E9: 0 | F9: 300
A10: 46244 | B10: 5 | C10: Cash | D10: Receive Payment for IT consulting | E10: 4500 | F10: 0
A11: 46244 | B11: 5 | C11: ='Chart or Accounts'!B10 -> Service Revenue | D11: Receive Payment for IT consulting | E11: 0 | F11: 4500
A12: 46246 | B12: 6 | C12: ='Chart or Accounts'!B4 -> Prepaid Insurance | D12: Paid 1-year Insurance Premium | E12: 1200 | F12: 0
A13: 46246 | B13: 6 | C13: Cash | D13: Paid 1-year Insurance Premium | E13: 0 | F13: 1200
A14: 46249 | B14: 7 | C14: ='Chart or Accounts'!B3 -> Accounts Receivable | D14: Billed Client for Software development | E14: 3000 | F14: 0
A15: 46249 | B15: 7 | C15: ='Chart or Accounts'!B10 -> Service Revenue | D15: Billed Client for Software development | E15: 0 | F15: 3000
A16: 46252 | B16: 8 | C16: Cash | D16: Collected partial payment from client | E16: 1500 | F16: 0
A17: 46252 | B17: 8 | C17: ='Chart or Accounts'!B3 -> Accounts Receivable | D17: Collected partial payment from client | E17: 0 | F17: 1500
A18: 46256 | B18: 9 | C18: ='Chart or Accounts'!B6 -> Accounts Payable | D18: Paid vendor towards equipment debt | E18: 1000 | F18: 0
A19: 46256 | B19: 9 | C19: Cash | D19: Paid vendor towards equipment debt | E19: 0 | F19: 1000
A20: 46259 | B20: 10 | C20: Cash | D20: Advanced payment for future project | E20: 2000 | F20: 0
A21: 46259 | B21: 10 | C21: ='Chart or Accounts'!B8 -> Unearned Revenue | D21: Advanced payment for future project | E21: 0 | F21: 2000
A22: 46262 | B22: 11 | C22: ='Chart or Accounts'!B13 -> Salaries Expense | D22: Paid staff monthly salaries | E22: 1800 | F22: 0
A23: 46262 | B23: 11 | C23: Cash | D23: Paid staff monthly salaries | E23: 0 | F23: 1800
A24: 46265 | B24: 12 | C24: ='Chart or Accounts'!B14 -> Insurance Expense | D24: Record August insurance adjustment | E24: 100 | F24: 0
A25: 46265 | B25: 12 | C25: ='Chart or Accounts'!B4 -> Prepaid Insurance | D25: Record August insurance adjustment | E25: 0 | F25: 100

Sheet General Ledger
A1: Account No | B1: Account Name | C1: Account Type | D1: Total Debits | E1: Total Credits | F1: Balance
A2: 101 | B2: =_xlfn.XLOOKUP(Table4[[#This Row],[Account No]],Table2[Account No],Table2[Account Name],"Not Found") -> Cash | C2: =_xlfn.XLOOKUP(Table4[[#This Row],[Account No]],Table2[Account No],Table2[Account Type],"Not Found") -> Assets | D2: =SUMIFS(Journal!E:E,Journal!C:C,Table4[[#This Row],[Account Name]]) -> 18000 | E2: =SUMIFS(Journal!F:F,Journal!C:C,Table4[[#This Row],[Account Name]]) -> 5500 | F2: =IF(OR(C2="Assets", C2="Expense"), D2-E2, E2-D2) -> 12500
A3: 102 | B3: =_xlfn.XLOOKUP(Table4[[#This Row],[Account No]],Table2[Account No],Table2[Account Name],"Not Found") -> Accounts Receivable | C3: =_xlfn.XLOOKUP(Table4[[#This Row],[Account No]],Table2[Account No],Table2[Account Type],"Not Found") -> Assets | D3: =SUMIFS(Journal!E:E,Journal!C:C,Table4[[#This Row],[Account Name]]) -> 3000 | E3: =SUMIFS(Journal!F:F,Journal!C:C,Table4[[#This Row],[Account Name]]) -> 1500 | F3: =IF(OR(C3="Assets", C3="Expense"), D3-E3, E3-D3) -> 1500
A4: 103 | B4: =_xlfn.XLOOKUP(Table4[[#This Row],[Account No]],Table2[Account No],Table2[Account Name],"Not Found") -> Prepaid Insurance | C4: =_xlfn.XLOOKUP(Table4[[#This Row],[Account No]],Table2[Account No],Table2[Account Type],"Not Found") -> Assets | D4: =SUMIFS(Journal!E:E,Journal!C:C,Table4[[#This Row],[Account Name]]) -> 1200 | E4: =SUMIFS(Journal!F:F,Journal!C:C,Table4[[#This Row],[Account Name]]) -> 100 | F4: =IF(OR(C4="Assets", C4="Expense"), D4-E4, E4-D4) -> 1100
A5: 104 | B5: =_xlfn.XLOOKUP(Table4[[#This Row],[Account No]],Table2[Account No],Table2[Account Name],"Not Found") -> Office Equipments | C5: =_xlfn.XLOOKUP(Table4[[#This Row],[Account No]],Table2[Account No],Table2[Account Type],"Not Found") -> Assets | D5: =SUMIFS(Journal!E:E,Journal!C:C,Table4[[#This Row],[Account Name]]) -> 3500 | E5: =SUMIFS(Journal!F:F,Journal!C:C,Table4[[#This Row],[Account Name]]) -> 0 | F5: =IF(OR(C5="Assets", C5="Expense"), D5-E5, E5-D5) -> 3500
A6: 201 | B6: =_xlfn.XLOOKUP(Table4[[#This Row],[Account No]],Table2[Account No],Table2[Account Name],"Not Found") -> Accounts Payable | C6: =_xlfn.XLOOKUP(Table4[[#This Row],[Account No]],Table2[Account No],Table2[Account Type],"Not Found") -> Liability | D6: =SUMIFS(Journal!E:E,Journal!C:C,Table4[[#This Row],[Account Name]]) -> 1000 | E6: =SUMIFS(Journal!F:F,Journal!C:C,Table4[[#This Row],[Account Name]]) -> 3500 | F6: =IF(OR(C6="Assets", C6="Expense"), D6-E6, E6-D6) -> 2500
A7: 202 | B7: =_xlfn.XLOOKUP(Table4[[#This Row],[Account No]],Table2[Account No],Table2[Account Name],"Not Found") -> Salaries Payable | C7: =_xlfn.XLOOKUP(Table4[[#This Row],[Account No]],Table2[Account No],Table2[Account Type],"Not Found") -> Liability | D7: =SUMIFS(Journal!E:E,Journal!C:C,Table4[[#This Row],[Account Name]]) -> 0 | E7: =SUMIFS(Journal!F:F,Journal!C:C,Table4[[#This Row],[Account Name]]) -> 0 | F7: =IF(OR(C7="Assets", C7="Expense"), D7-E7, E7-D7) -> 0
A8: 203 | B8: =_xlfn.XLOOKUP(Table4[[#This Row],[Account No]],Table2[Account No],Table2[Account Name],"Not Found") -> Unearned Revenue | C8: =_xlfn.XLOOKUP(Table4[[#This Row],[Account No]],Table2[Account No],Table2[Account Type],"Not Found") -> Liability | D8: =SUMIFS(Journal!E:E,Journal!C:C,Table4[[#This Row],[Account Name]]) -> 0 | E8: =SUMIFS(Journal!F:F,Journal!C:C,Table4[[#This Row],[Account Name]]) -> 2000 | F8: =IF(OR(C8="Assets", C8="Expense"), D8-E8, E8-D8) -> 2000
A9: 301 | B9: =_xlfn.XLOOKUP(Table4[[#This Row],[Account No]],Table2[Account No],Table2[Account Name],"Not Found") -> Owner's Capital | C9: =_xlfn.XLOOKUP(Table4[[#This Row],[Account No]],Table2[Account No],Table2[Account Type],"Not Found") -> Equity | D9: =SUMIFS(Journal!E:E,Journal!C:C,Table4[[#This Row],[Account Name]]) -> 0 | E9: =SUMIFS(Journal!F:F,Journal!C:C,Table4[[#This Row],[Account Name]]) -> 10000 | F9: =IF(OR(C9="Assets", C9="Expense"), D9-E9, E9-D9) -> 10000
A10: 401 | B10: =_xlfn.XLOOKUP(Table4[[#This Row],[Account No]],Table2[Account No],Table2[Account Name],"Not Found") -> Service Revenue | C10: =_xlfn.XLOOKUP(Table4[[#This Row],[Account No]],Table2[Account No],Table2[Account Type],"Not Found") -> Revenue | D10: =SUMIFS(Journal!E:E,Journal!C:C,Table4[[#This Row],[Account Name]]) -> 0 | E10: =SUMIFS(Journal!F:F,Journal!C:C,Table4[[#This Row],[Account Name]]) -> 7500 | F10: =IF(OR(C10="Assets", C10="Expense"), D10-E10, E10-D10) -> 7500
A11: 501 | B11: =_xlfn.XLOOKUP(Table4[[#This Row],[Account No]],Table2[Account No],Table2[Account Name],"Not Found") -> Rent Expense | C11: =_xlfn.XLOOKUP(Table4[[#This Row],[Account No]],Table2[Account No],Table2[Account Type],"Not Found") -> Expense | D11: =SUMIFS(Journal!E:E,Journal!C:C,Table4[[#This Row],[Account Name]]) -> 1200 | E11: =SUMIFS(Journal!F:F,Journal!C:C,Table4[[#This Row],[Account Name]]) -> 0 | F11: =IF(OR(C11="Assets", C11="Expense"), D11-E11, E11-D11) -> 1200
A12: 502 | B12: =_xlfn.XLOOKUP(Table4[[#This Row],[Account No]],Table2[Account No],Table2[Account Name],"Not Found") -> Office Supplies Expenses | C12: =_xlfn.XLOOKUP(Table4[[#This Row],[Account No]],Table2[Account No],Table2[Account Type],"Not Found") -> Expense | D12: =SUMIFS(Journal!E:E,Journal!C:C,Table4[[#This Row],[Account Name]]) -> 300 | E12: =SUMIFS(Journal!F:F,Journal!C:C,Table4[[#This Row],[Account Name]]) -> 0 | F12: =IF(OR(C12="Assets", C12="Expense"), D12-E12, E12-D12) -> 300
A13: 503 | B13: =_xlfn.XLOOKUP(Table4[[#This Row],[Account No]],Table2[Account No],Table2[Account Name],"Not Found") -> Salaries Expense | C13: =_xlfn.XLOOKUP(Table4[[#This Row],[Account No]],Table2[Account No],Table2[Account Type],"Not Found") -> Expense | D13: =SUMIFS(Journal!E:E,Journal!C:C,Table4[[#This Row],[Account Name]]) -> 1800 | E13: =SUMIFS(Journal!F:F,Journal!C:C,Table4[[#This Row],[Account Name]]) -> 0 | F13: =IF(OR(C13="Assets", C13="Expense"), D13-E13, E13-D13) -> 1800
A14: 504 | B14: =_xlfn.XLOOKUP(Table4[[#This Row],[Account No]],Table2[Account No],Table2[Account Name],"Not Found") -> Insurance Expense | C14: =_xlfn.XLOOKUP(Table4[[#This Row],[Account No]],Table2[Account No],Table2[Account Type],"Not Found") -> Expense | D14: =SUMIFS(Journal!E:E,Journal!C:C,Table4[[#This Row],[Account Name]]) -> 100 | E14: =SUMIFS(Journal!F:F,Journal!C:C,Table4[[#This Row],[Account Name]]) -> 0 | F14: =IF(OR(C14="Assets", C14="Expense"), D14-E14, E14-D14) -> 100

Sheet Trial Balance
A1: Account No | B1: Account Name | C1: Debit | D1: Credit
A2: 101 | B2: =_xlfn.XLOOKUP(Table5[[#This Row],[Account No]],Table4[Account No],Table4[Account Name],"Not Found") -> Cash | C2: =IF(OR(_xlfn.XLOOKUP(Table5[[#This Row],[Account Name ]],'General Ledger'!B:B,'General Ledger'!C:C)="Assets", _xlfn.XLOOKUP(Table5[[#This Row],[Account Name ]],'General Ledger'!B:B,'General Ledger'!C:C)="Expense"),_xlfn.XLOOKUP(Table5[[#This Row],[Account Name ]],'General Ledger'!B:B,'General Ledger'!F:F), 0) -> 12500 | D2: =IF(OR(_xlfn.XLOOKUP(Table5[[#This Row],[Account Name ]],'General Ledger'!B:B,'General Ledger'!C:C)="Liability", _xlfn.XLOOKUP(Table5[[#This Row],[Account Name ]],'General Ledger'!B:B,'General Ledger'!C:C)="Equity",_xlfn.XLOOKUP(Table5[[#This Row],[Account Name ]],'General Ledger'!B:B,'General Ledger'!C:C)="Revenue"), _xlfn.XLOOKUP(Table5[[#This Row],[Account Name ]],'General Ledger'!B:B,'General Ledger'!F:F),0) -> 0
A3: 102 | B3: =_xlfn.XLOOKUP(Table5[[#This Row],[Account No]],Table4[Account No],Table4[Account Name],"Not Found") -> Accounts Receivable | C3: =IF(OR(_xlfn.XLOOKUP(Table5[[#This Row],[Account Name ]],'General Ledger'!B:B,'General Ledger'!C:C)="Assets", _xlfn.XLOOKUP(Table5[[#This Row],[Account Name ]],'General Ledger'!B:B,'General Ledger'!C:C)="Expense"),_xlfn.XLOOKUP(Table5[[#This Row],[Account Name ]],'General Ledger'!B:B,'General Ledger'!F:F), 0) -> 1500 | D3: =IF(OR(_xlfn.XLOOKUP(Table5[[#This Row],[Account Name ]],'General Ledger'!B:B,'General Ledger'!C:C)="Liability", _xlfn.XLOOKUP(Table5[[#This Row],[Account Name ]],'General Ledger'!B:B,'General Ledger'!C:C)="Equity",_xlfn.XLOOKUP(Table5[[#This Row],[Account Name ]],'General Ledger'!B:B,'General Ledger'!C:C)="Revenue"), _xlfn.XLOOKUP(Table5[[#This Row],[Account Name ]],'General Ledger'!B:B,'General Ledger'!F:F),0) -> 0
A4: 103 | B4: =_xlfn.XLOOKUP(Table5[[#This Row],[Account No]],Table4[Account No],Table4[Account Name],"Not Found") -> Prepaid Insurance | C4: =IF(OR(_xlfn.XLOOKUP(Table5[[#This Row],[Account Name ]],'General Ledger'!B:B,'General Ledger'!C:C)="Assets", _xlfn.XLOOKUP(Table5[[#This Row],[Account Name ]],'General Ledger'!B:B,'General Ledger'!C:C)="Expense"),_xlfn.XLOOKUP(Table5[[#This Row],[Account Name ]],'General Ledger'!B:B,'General Ledger'!F:F), 0) -> 1100 | D4: =IF(OR(_xlfn.XLOOKUP(Table5[[#This Row],[Account Name ]],'General Ledger'!B:B,'General Ledger'!C:C)="Liability", _xlfn.XLOOKUP(Table5[[#This Row],[Account Name ]],'General Ledger'!B:B,'General Ledger'!C:C)="Equity",_xlfn.XLOOKUP(Table5[[#This Row],[Account Name ]],'General Ledger'!B:B,'General Ledger'!C:C)="Revenue"), _xlfn.XLOOKUP(Table5[[#This Row],[Account Name ]],'General Ledger'!B:B,'General Ledger'!F:F),0) -> 0
A5: 104 | B5: =_xlfn.XLOOKUP(Table5[[#This Row],[Account No]],Table4[Account No],Table4[Account Name],"Not Found") -> Office Equipments | C5: =IF(OR(_xlfn.XLOOKUP(Table5[[#This Row],[Account Name ]],'General Ledger'!B:B,'General Ledger'!C:C)="Assets", _xlfn.XLOOKUP(Table5[[#This Row],[Account Name ]],'General Ledger'!B:B,'General Ledger'!C:C)="Expense"),_xlfn.XLOOKUP(Table5[[#This Row],[Account Name ]],'General Ledger'!B:B,'General Ledger'!F:F), 0) -> 3500 | D5: =IF(OR(_xlfn.XLOOKUP(Table5[[#This Row],[Account Name ]],'General Ledger'!B:B,'General Ledger'!C:C)="Liability", _xlfn.XLOOKUP(Table5[[#This Row],[Account Name ]],'General Ledger'!B:B,'General Ledger'!C:C)="Equity",_xlfn.XLOOKUP(Table5[[#This Row],[Account Name ]],'General Ledger'!B:B,'General Ledger'!C:C)="Revenue"), _xlfn.XLOOKUP(Table5[[#This Row],[Account Name ]],'General Ledger'!B:B,'General Ledger'!F:F),0) -> 0
A6: 201 | B6: =_xlfn.XLOOKUP(Table5[[#This Row],[Account No]],Table4[Account No],Table4[Account Name],"Not Found") -> Accounts Payable | C6: =IF(OR(_xlfn.XLOOKUP(Table5[[#This Row],[Account Name ]],'General Ledger'!B:B,'General Ledger'!C:C)="Assets", _xlfn.XLOOKUP(Table5[[#This Row],[Account Name ]],'General Ledger'!B:B,'General Ledger'!C:C)="Expense"),_xlfn.XLOOKUP(Table5[[#This Row],[Account Name ]],'General Ledger'!B:B,'General Ledger'!F:F), 0) -> 0 | D6: =IF(OR(_xlfn.XLOOKUP(Table5[[#This Row],[Account Name ]],'General Ledger'!B:B,'General Ledger'!C:C)="Liability", _xlfn.XLOOKUP(Table5[[#This Row],[Account Name ]],'General Ledger'!B:B,'General Ledger'!C:C)="Equity",_xlfn.XLOOKUP(Table5[[#This Row],[Account Name ]],'General Ledger'!B:B,'General Ledger'!C:C)="Revenue"), _xlfn.XLOOKUP(Table5[[#This Row],[Account Name ]],'General Ledger'!B:B,'General Ledger'!F:F),0) -> 2500
A7: 202 | B7: =_xlfn.XLOOKUP(Table5[[#This Row],[Account No]],Table4[Account No],Table4[Account Name],"Not Found") -> Salaries Payable | C7: =IF(OR(_xlfn.XLOOKUP(Table5[[#This Row],[Account Name ]],'General Ledger'!B:B,'General Ledger'!C:C)="Assets", _xlfn.XLOOKUP(Table5[[#This Row],[Account Name ]],'General Ledger'!B:B,'General Ledger'!C:C)="Expense"),_xlfn.XLOOKUP(Table5[[#This Row],[Account Name ]],'General Ledger'!B:B,'General Ledger'!F:F), 0) -> 0 | D7: =IF(OR(_xlfn.XLOOKUP(Table5[[#This Row],[Account Name ]],'General Ledger'!B:B,'General Ledger'!C:C)="Liability", _xlfn.XLOOKUP(Table5[[#This Row],[Account Name ]],'General Ledger'!B:B,'General Ledger'!C:C)="Equity",_xlfn.XLOOKUP(Table5[[#This Row],[Account Name ]],'General Ledger'!B:B,'General Ledger'!C:C)="Revenue"), _xlfn.XLOOKUP(Table5[[#This Row],[Account Name ]],'General Ledger'!B:B,'General Ledger'!F:F),0) -> 0
A8: 203 | B8: =_xlfn.XLOOKUP(Table5[[#This Row],[Account No]],Table4[Account No],Table4[Account Name],"Not Found") -> Unearned Revenue | C8: =IF(OR(_xlfn.XLOOKUP(Table5[[#This Row],[Account Name ]],'General Ledger'!B:B,'General Ledger'!C:C)="Assets", _xlfn.XLOOKUP(Table5[[#This Row],[Account Name ]],'General Ledger'!B:B,'General Ledger'!C:C)="Expense"),_xlfn.XLOOKUP(Table5[[#This Row],[Account Name ]],'General Ledger'!B:B,'General Ledger'!F:F), 0) -> 0 | D8: =IF(OR(_xlfn.XLOOKUP(Table5[[#This Row],[Account Name ]],'General Ledger'!B:B,'General Ledger'!C:C)="Liability", _xlfn.XLOOKUP(Table5[[#This Row],[Account Name ]],'General Ledger'!B:B,'General Ledger'!C:C)="Equity",_xlfn.XLOOKUP(Table5[[#This Row],[Account Name ]],'General Ledger'!B:B,'General Ledger'!C:C)="Revenue"), _xlfn.XLOOKUP(Table5[[#This Row],[Account Name ]],'General Ledger'!B:B,'General Ledger'!F:F),0) -> 2000
A9: 301 | B9: =_xlfn.XLOOKUP(Table5[[#This Row],[Account No]],Table4[Account No],Table4[Account Name],"Not Found") -> Owner's Capital | C9: =IF(OR(_xlfn.XLOOKUP(Table5[[#This Row],[Account Name ]],'General Ledger'!B:B,'General Ledger'!C:C)="Assets", _xlfn.XLOOKUP(Table5[[#This Row],[Account Name ]],'General Ledger'!B:B,'General Ledger'!C:C)="Expense"),_xlfn.XLOOKUP(Table5[[#This Row],[Account Name ]],'General Ledger'!B:B,'General Ledger'!F:F), 0) -> 0 | D9: =IF(OR(_xlfn.XLOOKUP(Table5[[#This Row],[Account Name ]],'General Ledger'!B:B,'General Ledger'!C:C)="Liability", _xlfn.XLOOKUP(Table5[[#This Row],[Account Name ]],'General Ledger'!B:B,'General Ledger'!C:C)="Equity",_xlfn.XLOOKUP(Table5[[#This Row],[Account Name ]],'General Ledger'!B:B,'General Ledger'!C:C)="Revenue"), _xlfn.XLOOKUP(Table5[[#This Row],[Account Name ]],'General Ledger'!B:B,'General Ledger'!F:F),0) -> 10000
A10: 401 | B10: =_xlfn.XLOOKUP(Table5[[#This Row],[Account No]],Table4[Account No],Table4[Account Name],"Not Found") -> Service Revenue | C10: =IF(OR(_xlfn.XLOOKUP(Table5[[#This Row],[Account Name ]],'General Ledger'!B:B,'General Ledger'!C:C)="Assets", _xlfn.XLOOKUP(Table5[[#This Row],[Account Name ]],'General Ledger'!B:B,'General Ledger'!C:C)="Expense"),_xlfn.XLOOKUP(Table5[[#This Row],[Account Name ]],'General Ledger'!B:B,'General Ledger'!F:F), 0) -> 0 | D10: =IF(OR(_xlfn.XLOOKUP(Table5[[#This Row],[Account Name ]],'General Ledger'!B:B,'General Ledger'!C:C)="Liability", _xlfn.XLOOKUP(Table5[[#This Row],[Account Name ]],'General Ledger'!B:B,'General Ledger'!C:C)="Equity",_xlfn.XLOOKUP(Table5[[#This Row],[Account Name ]],'General Ledger'!B:B,'General Ledger'!C:C)="Revenue"), _xlfn.XLOOKUP(Table5[[#This Row],[Account Name ]],'General Ledger'!B:B,'General Ledger'!F:F),0) -> 7500
A11: 501 | B11: =_xlfn.XLOOKUP(Table5[[#This Row],[Account No]],Table4[Account No],Table4[Account Name],"Not Found") -> Rent Expense | C11: =IF(OR(_xlfn.XLOOKUP(Table5[[#This Row],[Account Name ]],'General Ledger'!B:B,'General Ledger'!C:C)="Assets", _xlfn.XLOOKUP(Table5[[#This Row],[Account Name ]],'General Ledger'!B:B,'General Ledger'!C:C)="Expense"),_xlfn.XLOOKUP(Table5[[#This Row],[Account Name ]],'General Ledger'!B:B,'General Ledger'!F:F), 0) -> 1200 | D11: =IF(OR(_xlfn.XLOOKUP(Table5[[#This Row],[Account Name ]],'General Ledger'!B:B,'General Ledger'!C:C)="Liability", _xlfn.XLOOKUP(Table5[[#This Row],[Account Name ]],'General Ledger'!B:B,'General Ledger'!C:C)="Equity",_xlfn.XLOOKUP(Table5[[#This Row],[Account Name ]],'General Ledger'!B:B,'General Ledger'!C:C)="Revenue"), _xlfn.XLOOKUP(Table5[[#This Row],[Account Name ]],'General Ledger'!B:B,'General Ledger'!F:F),0) -> 0
A12: 502 | B12: =_xlfn.XLOOKUP(Table5[[#This Row],[Account No]],Table4[Account No],Table4[Account Name],"Not Found") -> Office Supplies Expenses | C12: =IF(OR(_xlfn.XLOOKUP(Table5[[#This Row],[Account Name ]],'General Ledger'!B:B,'General Ledger'!C:C)="Assets", _xlfn.XLOOKUP(Table5[[#This Row],[Account Name ]],'General Ledger'!B:B,'General Ledger'!C:C)="Expense"),_xlfn.XLOOKUP(Table5[[#This Row],[Account Name ]],'General Ledger'!B:B,'General Ledger'!F:F), 0) -> 300 | D12: =IF(OR(_xlfn.XLOOKUP(Table5[[#This Row],[Account Name ]],'General Ledger'!B:B,'General Ledger'!C:C)="Liability", _xlfn.XLOOKUP(Table5[[#This Row],[Account Name ]],'General Ledger'!B:B,'General Ledger'!C:C)="Equity",_xlfn.XLOOKUP(Table5[[#This Row],[Account Name ]],'General Ledger'!B:B,'General Ledger'!C:C)="Revenue"), _xlfn.XLOOKUP(Table5[[#This Row],[Account Name ]],'General Ledger'!B:B,'General Ledger'!F:F),0) -> 0
A13: 503 | B13: =_xlfn.XLOOKUP(Table5[[#This Row],[Account No]],Table4[Account No],Table4[Account Name],"Not Found") -> Salaries Expense | C13: =IF(OR(_xlfn.XLOOKUP(Table5[[#This Row],[Account Name ]],'General Ledger'!B:B,'General Ledger'!C:C)="Assets", _xlfn.XLOOKUP(Table5[[#This Row],[Account Name ]],'General Ledger'!B:B,'General Ledger'!C:C)="Expense"),_xlfn.XLOOKUP(Table5[[#This Row],[Account Name ]],'General Ledger'!B:B,'General Ledger'!F:F), 0) -> 1800 | D13: =IF(OR(_xlfn.XLOOKUP(Table5[[#This Row],[Account Name ]],'General Ledger'!B:B,'General Ledger'!C:C)="Liability", _xlfn.XLOOKUP(Table5[[#This Row],[Account Name ]],'General Ledger'!B:B,'General Ledger'!C:C)="Equity",_xlfn.XLOOKUP(Table5[[#This Row],[Account Name ]],'General Ledger'!B:B,'General Ledger'!C:C)="Revenue"), _xlfn.XLOOKUP(Table5[[#This Row],[Account Name ]],'General Ledger'!B:B,'General Ledger'!F:F),0) -> 0
A14: 504 | B14: =_xlfn.XLOOKUP(Table5[[#This Row],[Account No]],Table4[Account No],Table4[Account Name],"Not Found") -> Insurance Expense | C14: =IF(OR(_xlfn.XLOOKUP(Table5[[#This Row],[Account Name ]],'General Ledger'!B:B,'General Ledger'!C:C)="Assets", _xlfn.XLOOKUP(Table5[[#This Row],[Account Name ]],'General Ledger'!B:B,'General Ledger'!C:C)="Expense"),_xlfn.XLOOKUP(Table5[[#This Row],[Account Name ]],'General Ledger'!B:B,'General Ledger'!F:F), 0) -> 100 | D14: =IF(OR(_xlfn.XLOOKUP(Table5[[#This Row],[Account Name ]],'General Ledger'!B:B,'General Ledger'!C:C)="Liability", _xlfn.XLOOKUP(Table5[[#This Row],[Account Name ]],'General Ledger'!B:B,'General Ledger'!C:C)="Equity",_xlfn.XLOOKUP(Table5[[#This Row],[Account Name ]],'General Ledger'!B:B,'General Ledger'!C:C)="Revenue"), _xlfn.XLOOKUP(Table5[[#This Row],[Account Name ]],'General Ledger'!B:B,'General Ledger'!F:F),0) -> 0
A15: Total Balance | C15: =SUM(C2:C14) -> 22000 | D15: =SUM(D2:D14) -> 22000

Sheet Income Statement
A1: Income Statement of Aug 2026
A2: Line Item | B2: Amount ($)
A3: Revenues
A4: Service Revenue | B4: ='Trial Balance'!D10 -> 7500
A6: Total Revenue | B6: =SUM(B4) -> 7500
A8: Operating Expenses
A9: Rent Expense | B9: ='Trial Balance'!C11 -> 1200
A10: ='Trial Balance'!B12 -> Office Supplies Expenses | B10: ='Trial Balance'!C12 -> 300
A11: ='Trial Balance'!B13 -> Salaries Expense | B11: ='Trial Balance'!C13 -> 1800
A12: ='Trial Balance'!B14 -> Insurance Expense | B12: ='Trial Balance'!C14 -> 100
A14: Total Expenses | B14: =SUM(B9:B12) -> 3400
A16: Net Income | B16: =B6-B14 -> 4100

Sheet Balance Sheet
A1: Balance Sheet of Aug 2026
A2: Assets | B2: Amount ($)
A3: ='Trial Balance'!B2 -> Cash | B3: ='Trial Balance'!C2 -> 12500
A4: ='Trial Balance'!B3 -> Accounts Receivable | B4: ='Trial Balance'!C3 -> 1500
A5: ='Trial Balance'!B4 -> Prepaid Insurance | B5: ='Trial Balance'!C4 -> 1100
A6: ='Trial Balance'!B5 -> Office Equipments | B6: ='Trial Balance'!C5 -> 3500
A7: Total Assets | B7: =SUM(B3:B6) -> 18600
A8: Liabilities
A9: ='Trial Balance'!B6 -> Accounts Payable | B9: ='Trial Balance'!D6 -> 2500
A10: ='Trial Balance'!B7 -> Salaries Payable | B10: 0
A11: ='Trial Balance'!B8 -> Unearned Revenue | B11: ='Trial Balance'!D8 -> 2000
A12: Total Liabilities | B12: =SUM(B9:B11) -> 4500
A13: Equity
A14: ='Trial Balance'!B9 -> Owner's Capital | B14: ='Trial Balance'!D9 -> 10000
A15: Retained Earnings | B15: ='Income Statement'!B16 -> 4100
A16: Total Equity | B16: =SUM(B14:B15) -> 14100
A18: Total Liabilities & Equities | B18: =SUM(B12,B16) -> 18600
A20: =IF(B7 =B18, "BALANCE SHEET BALANCED", "ERROR: UNBALANCED") -> BALANCE SHEET BALANCED
